fuzzy_set_arythmetic/__init__.py
fuzzy_set_arythmetic/alpha.py
fuzzy_set_arythmetic/alpha_cut.py
fuzzy_set_arythmetic/border.py
fuzzy_set_arythmetic/fuzzy_set.py
fuzzy_set_arythmetic/plot.py
fuzzy_set_arythmetic/t_norm.py
fuzzy_set_arythmetic/types.py
fuzzy_set_arythmetic-0.1.0.dist-info/METADATA
fuzzy_set_arythmetic-0.1.0.dist-info/WHEEL
fuzzy_set_arythmetic-0.1.0.dist-info/RECORD
