Metadata-Version: 2.3
Name: fuzzy-set-arythmetic
Version: 0.1.0
Summary: 
Author: Michał Kalenik
Author-email: mchl.klnk@gmail.com
Requires-Python: ^3.13
Classifier: Programming Language :: Python :: 3
Classifier: Programming Language :: Python :: 3.13
Requires-Dist: matplotlib (>=3.10.1,<4.0.0)
